[
    {
        "id": 1,
        "t1_average_reward": 50.0,
        "t2_average_reward": 147.01492537313433,
        "t3_average_reward": 150.0,
        "t1_number_of_solutions": 67,
        "t2_number_of_solutions": 67,
        "t3_number_of_solutions": 67,
        "number_of_final_solutions": 67,
        "results": [
            1.0,
            0.14925373134328357,
            0.2597402597402597,
            null
        ]
    },
    {
        "id": 2,
        "t1_average_reward": 50.74626865671642,
        "t2_average_reward": 148.50746268656715,
        "t3_average_reward": 149.2537313432836,
        "t1_number_of_solutions": 67,
        "t2_number_of_solutions": 67,
        "t3_number_of_solutions": 67,
        "number_of_final_solutions": 67,
        "results": [
            1.0,
            0.14925373134328357,
            0.2597402597402597,
            null
        ]
    },
    {
        "id": 3,
        "t1_average_reward": 50.74626865671642,
        "t2_average_reward": 149.2537313432836,
        "t3_average_reward": 149.2537313432836,
        "t1_number_of_solutions": 67,
        "t2_number_of_solutions": 67,
        "t3_number_of_solutions": 67,
        "number_of_final_solutions": 67,
        "results": [
            1.0,
            0.14925373134328357,
            0.2597402597402597,
            null
        ]
    },
    {
        "id": 4,
        "t1_average_reward": 49.25373134328358,
        "t2_average_reward": 150.7462686567164,
        "t3_average_reward": 147.76119402985074,
        "t1_number_of_solutions": 67,
        "t2_number_of_solutions": 67,
        "t3_number_of_solutions": 67,
        "number_of_final_solutions": 67,
        "results": [
            1.0,
            0.14925373134328357,
            0.2597402597402597,
            null
        ]
    },
    {
        "id": 5,
        "t1_average_reward": 44.02985074626866,
        "t2_average_reward": 147.76119402985074,
        "t3_average_reward": 146.26865671641792,
        "t1_number_of_solutions": 66,
        "t2_number_of_solutions": 67,
        "t3_number_of_solutions": 67,
        "number_of_final_solutions": 66,
        "results": [
            1.0,
            0.15151515151515152,
            0.2631578947368421,
            null
        ]
    },
    {
        "id": 6,
        "t1_average_reward": 51.492537313432834,
        "t2_average_reward": 148.50746268656715,
        "t3_average_reward": 144.77611940298507,
        "t1_number_of_solutions": 67,
        "t2_number_of_solutions": 67,
        "t3_number_of_solutions": 67,
        "number_of_final_solutions": 67,
        "results": [
            1.0,
            0.14925373134328357,
            0.2597402597402597,
            null
        ]
    },
    {
        "id": 7,
        "t1_average_reward": 50.74626865671642,
        "t2_average_reward": 148.50746268656715,
        "t3_average_reward": 146.26865671641792,
        "t1_number_of_solutions": 66,
        "t2_number_of_solutions": 67,
        "t3_number_of_solutions": 67,
        "number_of_final_solutions": 66,
        "results": [
            1.0,
            0.15151515151515152,
            0.2631578947368421,
            null
        ]
    },
    {
        "id": 8,
        "t1_average_reward": 46.26865671641791,
        "t2_average_reward": 152.98507462686567,
        "t3_average_reward": 148.50746268656715,
        "t1_number_of_solutions": 67,
        "t2_number_of_solutions": 67,
        "t3_number_of_solutions": 67,
        "number_of_final_solutions": 67,
        "results": [
            1.0,
            0.14925373134328357,
            0.2597402597402597,
            null
        ]
    },
    {
        "id": 9,
        "t1_average_reward": 53.73134328358209,
        "t2_average_reward": 150.7462686567164,
        "t3_average_reward": 149.2537313432836,
        "t1_number_of_solutions": 66,
        "t2_number_of_solutions": 64,
        "t3_number_of_solutions": 62,
        "number_of_final_solutions": 58,
        "results": [
            1.0,
            0.1724137931034483,
            0.29411764705882354,
            null
        ]
    },
    {
        "id": 10,
        "t1_average_reward": 53.73134328358209,
        "t2_average_reward": 150.0,
        "t3_average_reward": 148.50746268656715,
        "t1_number_of_solutions": 65,
        "t2_number_of_solutions": 59,
        "t3_number_of_solutions": 66,
        "number_of_final_solutions": 56,
        "results": [
            0.8,
            0.14285714285714285,
            0.24242424242424243,
            null
        ]
    },
    {
        "id": 11,
        "t1_average_reward": 53.73134328358209,
        "t2_average_reward": 149.2537313432836,
        "t3_average_reward": 148.50746268656715,
        "t1_number_of_solutions": 64,
        "t2_number_of_solutions": 67,
        "t3_number_of_solutions": 66,
        "number_of_final_solutions": 63,
        "results": [
            1.0,
            0.15873015873015872,
            0.27397260273972607,
            null
        ]
    },
    {
        "id": 12,
        "t1_average_reward": 53.73134328358209,
        "t2_average_reward": 150.0,
        "t3_average_reward": 149.2537313432836,
        "t1_number_of_solutions": 65,
        "t2_number_of_solutions": 64,
        "t3_number_of_solutions": 64,
        "number_of_final_solutions": 59,
        "results": [
            0.7,
            0.11864406779661017,
            0.20289855072463767,
            null
        ]
    },
    {
        "id": 13,
        "t1_average_reward": 53.73134328358209,
        "t2_average_reward": 152.98507462686567,
        "t3_average_reward": 147.76119402985074,
        "t1_number_of_solutions": 62,
        "t2_number_of_solutions": 46,
        "t3_number_of_solutions": 47,
        "number_of_final_solutions": 30,
        "results": [
            0.5,
            0.16666666666666666,
            0.25,
            null
        ]
    },
    {
        "id": 14,
        "t1_average_reward": 54.47761194029851,
        "t2_average_reward": 150.0,
        "t3_average_reward": 149.2537313432836,
        "t1_number_of_solutions": 61,
        "t2_number_of_solutions": 46,
        "t3_number_of_solutions": 42,
        "number_of_final_solutions": 25,
        "results": [
            0.4,
            0.16,
            0.22857142857142856,
            null
        ]
    },
    {
        "id": 15,
        "t1_average_reward": 55.223880597014926,
        "t2_average_reward": 148.50746268656715,
        "t3_average_reward": 147.76119402985074,
        "t1_number_of_solutions": 62,
        "t2_number_of_solutions": 41,
        "t3_number_of_solutions": 49,
        "number_of_final_solutions": 29,
        "results": [
            0.3,
            0.10344827586206896,
            0.15384615384615385,
            null
        ]
    },
    {
        "id": 16,
        "t1_average_reward": 53.73134328358209,
        "t2_average_reward": 149.2537313432836,
        "t3_average_reward": 147.76119402985074,
        "t1_number_of_solutions": 64,
        "t2_number_of_solutions": 50,
        "t3_number_of_solutions": 50,
        "number_of_final_solutions": 35,
        "results": [
            0.2,
            0.05714285714285714,
            0.08888888888888888,
            null
        ]
    },
    {
        "id": 17,
        "t1_average_reward": 54.47761194029851,
        "t2_average_reward": 150.0,
        "t3_average_reward": 150.0,
        "t1_number_of_solutions": 66,
        "t2_number_of_solutions": 59,
        "t3_number_of_solutions": 66,
        "number_of_final_solutions": 57,
        "results": [
            0.7,
            0.12280701754385964,
            0.208955223880597,
            null
        ]
    },
    {
        "id": 18,
        "t1_average_reward": 53.73134328358209,
        "t2_average_reward": 150.0,
        "t3_average_reward": 149.2537313432836,
        "t1_number_of_solutions": 67,
        "t2_number_of_solutions": 64,
        "t3_number_of_solutions": 65,
        "number_of_final_solutions": 63,
        "results": [
            0.8,
            0.12698412698412698,
            0.2191780821917808,
            null
        ]
    },
    {
        "id": 19,
        "t1_average_reward": 53.73134328358209,
        "t2_average_reward": 150.0,
        "t3_average_reward": 150.0,
        "t1_number_of_solutions": 64,
        "t2_number_of_solutions": 63,
        "t3_number_of_solutions": 67,
        "number_of_final_solutions": 60,
        "results": [
            0.8,
            0.13333333333333333,
            0.2285714285714286,
            null
        ]
    },
    {
        "id": 20,
        "t1_average_reward": 54.47761194029851,
        "t2_average_reward": 150.0,
        "t3_average_reward": 151.49253731343285,
        "t1_number_of_solutions": 66,
        "t2_number_of_solutions": 64,
        "t3_number_of_solutions": 67,
        "number_of_final_solutions": 63,
        "results": [
            1.0,
            0.15873015873015872,
            0.27397260273972607,
            null
        ]
    },
    {
        "id": 21,
        "t1_average_reward": 54.47761194029851,
        "t2_average_reward": 150.0,
        "t3_average_reward": 150.0,
        "t1_number_of_solutions": 65,
        "t2_number_of_solutions": 56,
        "t3_number_of_solutions": 62,
        "number_of_final_solutions": 50,
        "results": [
            0.8,
            0.16,
            0.26666666666666666,
            null
        ]
    },
    {
        "id": 22,
        "t1_average_reward": 53.73134328358209,
        "t2_average_reward": 152.98507462686567,
        "t3_average_reward": 148.50746268656715,
        "t1_number_of_solutions": 66,
        "t2_number_of_solutions": 52,
        "t3_number_of_solutions": 58,
        "number_of_final_solutions": 45,
        "results": [
            0.5,
            0.1111111111111111,
            0.1818181818181818,
            null
        ]
    },
    {
        "id": 23,
        "t1_average_reward": 54.47761194029851,
        "t2_average_reward": 150.0,
        "t3_average_reward": 150.0,
        "t1_number_of_solutions": 65,
        "t2_number_of_solutions": 55,
        "t3_number_of_solutions": 64,
        "number_of_final_solutions": 52,
        "results": [
            0.9,
            0.17307692307692307,
            0.2903225806451613,
            null
        ]
    },
    {
        "id": 24,
        "t1_average_reward": 53.73134328358209,
        "t2_average_reward": 150.0,
        "t3_average_reward": 148.50746268656715,
        "t1_number_of_solutions": 64,
        "t2_number_of_solutions": 50,
        "t3_number_of_solutions": 62,
        "number_of_final_solutions": 45,
        "results": [
            0.8,
            0.17777777777777778,
            0.2909090909090909,
            null
        ]
    },
    {
        "id": 25,
        "t1_average_reward": -165.67164179104478,
        "t2_average_reward": -216.4179104477612,
        "t3_average_reward": -55.97014925373134,
        "t1_number_of_solutions": 8,
        "t2_number_of_solutions": 7,
        "t3_number_of_solutions": 5,
        "number_of_final_solutions": 0,
        "results": [
            0.0,
            0.0,
            0.0,
            null
        ]
    },
    {
        "id": 26,
        "t1_average_reward": -147.76119402985074,
        "t2_average_reward": -145.52238805970148,
        "t3_average_reward": -79.85074626865672,
        "t1_number_of_solutions": 6,
        "t2_number_of_solutions": 10,
        "t3_number_of_solutions": 6,
        "number_of_final_solutions": 0,
        "results": [
            0.0,
            0.0,
            0.0,
            null
        ]
    },
    {
        "id": 27,
        "t1_average_reward": -261.94029850746267,
        "t2_average_reward": -420.8955223880597,
        "t3_average_reward": -120.14925373134328,
        "t1_number_of_solutions": 19,
        "t2_number_of_solutions": 13,
        "t3_number_of_solutions": 19,
        "number_of_final_solutions": 0,
        "results": [
            0.0,
            0.0,
            0.0,
            null
        ]
    },
    {
        "id": 28,
        "t1_average_reward": -235.07462686567163,
        "t2_average_reward": -83.58208955223881,
        "t3_average_reward": -2.985074626865672,
        "t1_number_of_solutions": 13,
        "t2_number_of_solutions": 11,
        "t3_number_of_solutions": 14,
        "number_of_final_solutions": 0,
        "results": [
            0.0,
            0.0,
            0.0,
            null
        ]
    },
    {
        "id": 29,
        "t1_average_reward": -225.37313432835822,
        "t2_average_reward": -247.01492537313433,
        "t3_average_reward": -155.97014925373134,
        "t1_number_of_solutions": 13,
        "t2_number_of_solutions": 10,
        "t3_number_of_solutions": 11,
        "number_of_final_solutions": 0,
        "results": [
            0.0,
            0.0,
            0.0,
            null
        ]
    },
    {
        "id": 30,
        "t1_average_reward": -163.43283582089552,
        "t2_average_reward": -115.67164179104478,
        "t3_average_reward": -53.73134328358209,
        "t1_number_of_solutions": 8,
        "t2_number_of_solutions": 8,
        "t3_number_of_solutions": 8,
        "number_of_final_solutions": 0,
        "results": [
            0.0,
            0.0,
            0.0,
            null
        ]
    },
    {
        "id": 31,
        "t1_average_reward": -249.2537313432836,
        "t2_average_reward": -316.4179104477612,
        "t3_average_reward": -194.77611940298507,
        "t1_number_of_solutions": 16,
        "t2_number_of_solutions": 11,
        "t3_number_of_solutions": 14,
        "number_of_final_solutions": 0,
        "results": [
            0.0,
            0.0,
            0.0,
            null
        ]
    },
    {
        "id": 32,
        "t1_average_reward": -125.3731343283582,
        "t2_average_reward": -90.29850746268657,
        "t3_average_reward": -161.19402985074626,
        "t1_number_of_solutions": 12,
        "t2_number_of_solutions": 10,
        "t3_number_of_solutions": 13,
        "number_of_final_solutions": 0,
        "results": [
            0.0,
            0.0,
            0.0,
            null
        ]
    },
    {
        "id": 33,
        "t1_average_reward": -135.07462686567163,
        "t2_average_reward": -24.62686567164179,
        "t3_average_reward": 41.04477611940298,
        "t1_number_of_solutions": 13,
        "t2_number_of_solutions": 9,
        "t3_number_of_solutions": 15,
        "number_of_final_solutions": 1,
        "results": [
            0.0,
            0.0,
            0.0,
            null
        ]
    },
    {
        "id": 34,
        "t1_average_reward": -60.44776119402985,
        "t2_average_reward": 0.0,
        "t3_average_reward": 26.865671641791046,
        "t1_number_of_solutions": 18,
        "t2_number_of_solutions": 15,
        "t3_number_of_solutions": 18,
        "number_of_final_solutions": 1,
        "results": [
            0.0,
            0.0,
            0.0,
            null
        ]
    },
    {
        "id": 35,
        "t1_average_reward": -100.0,
        "t2_average_reward": 0.0,
        "t3_average_reward": 26.865671641791046,
        "t1_number_of_solutions": 22,
        "t2_number_of_solutions": 16,
        "t3_number_of_solutions": 19,
        "number_of_final_solutions": 1,
        "results": [
            0.0,
            0.0,
            0.0,
            null
        ]
    },
    {
        "id": 36,
        "t1_average_reward": -80.59701492537313,
        "t2_average_reward": 25.37313432835821,
        "t3_average_reward": 52.985074626865675,
        "t1_number_of_solutions": 13,
        "t2_number_of_solutions": 19,
        "t3_number_of_solutions": 23,
        "number_of_final_solutions": 1,
        "results": [
            0.1,
            1.0,
            0.18181818181818182,
            null
        ]
    },
    {
        "id": 37,
        "t1_average_reward": -105.97014925373135,
        "t2_average_reward": -60.44776119402985,
        "t3_average_reward": 37.3134328358209,
        "t1_number_of_solutions": 10,
        "t2_number_of_solutions": 15,
        "t3_number_of_solutions": 13,
        "number_of_final_solutions": 1,
        "results": [
            0.0,
            0.0,
            0.0,
            null
        ]
    },
    {
        "id": 38,
        "t1_average_reward": -97.76119402985074,
        "t2_average_reward": 20.149253731343283,
        "t3_average_reward": 14.17910447761194,
        "t1_number_of_solutions": 11,
        "t2_number_of_solutions": 16,
        "t3_number_of_solutions": 13,
        "number_of_final_solutions": 0,
        "results": [
            0.0,
            0.0,
            0.0,
            null
        ]
    },
    {
        "id": 39,
        "t1_average_reward": -203.73134328358208,
        "t2_average_reward": -22.388059701492537,
        "t3_average_reward": 19.402985074626866,
        "t1_number_of_solutions": 12,
        "t2_number_of_solutions": 13,
        "t3_number_of_solutions": 23,
        "number_of_final_solutions": 2,
        "results": [
            0.1,
            0.5,
            0.16666666666666669,
            null
        ]
    },
    {
        "id": 40,
        "t1_average_reward": -113.43283582089552,
        "t2_average_reward": 38.059701492537314,
        "t3_average_reward": 23.134328358208954,
        "t1_number_of_solutions": 10,
        "t2_number_of_solutions": 18,
        "t3_number_of_solutions": 14,
        "number_of_final_solutions": 1,
        "results": [
            0.0,
            0.0,
            0.0,
            null
        ]
    },
    {
        "id": 41,
        "t1_average_reward": -5.223880597014926,
        "t2_average_reward": 63.43283582089552,
        "t3_average_reward": 91.7910447761194,
        "t1_number_of_solutions": 36,
        "t2_number_of_solutions": 36,
        "t3_number_of_solutions": 44,
        "number_of_final_solutions": 9,
        "results": [
            0.2,
            0.2222222222222222,
            0.2105263157894737,
            null
        ]
    },
    {
        "id": 42,
        "t1_average_reward": 4.477611940298507,
        "t2_average_reward": 84.32835820895522,
        "t3_average_reward": 91.7910447761194,
        "t1_number_of_solutions": 43,
        "t2_number_of_solutions": 34,
        "t3_number_of_solutions": 37,
        "number_of_final_solutions": 12,
        "results": [
            0.4,
            0.3333333333333333,
            0.3636363636363636,
            null
        ]
    },
    {
        "id": 43,
        "t1_average_reward": -36.56716417910448,
        "t2_average_reward": 81.34328358208955,
        "t3_average_reward": 82.08955223880596,
        "t1_number_of_solutions": 38,
        "t2_number_of_solutions": 44,
        "t3_number_of_solutions": 37,
        "number_of_final_solutions": 11,
        "results": [
            0.4,
            0.36363636363636365,
            0.380952380952381,
            null
        ]
    },
    {
        "id": 44,
        "t1_average_reward": -12.686567164179104,
        "t2_average_reward": 58.208955223880594,
        "t3_average_reward": 109.70149253731343,
        "t1_number_of_solutions": 34,
        "t2_number_of_solutions": 31,
        "t3_number_of_solutions": 48,
        "number_of_final_solutions": 10,
        "results": [
            0.2,
            0.2,
            0.20000000000000004,
            null
        ]
    },
    {
        "id": 45,
        "t1_average_reward": -44.02985074626866,
        "t2_average_reward": 78.35820895522389,
        "t3_average_reward": 88.80597014925372,
        "t1_number_of_solutions": 26,
        "t2_number_of_solutions": 41,
        "t3_number_of_solutions": 43,
        "number_of_final_solutions": 8,
        "results": [
            0.0,
            0.0,
            0.0,
            null
        ]
    },
    {
        "id": 46,
        "t1_average_reward": -23.134328358208954,
        "t2_average_reward": 67.16417910447761,
        "t3_average_reward": 85.07462686567165,
        "t1_number_of_solutions": 34,
        "t2_number_of_solutions": 37,
        "t3_number_of_solutions": 37,
        "number_of_final_solutions": 9,
        "results": [
            0.2,
            0.2222222222222222,
            0.2105263157894737,
            null
        ]
    },
    {
        "id": 47,
        "t1_average_reward": -15.671641791044776,
        "t2_average_reward": 85.82089552238806,
        "t3_average_reward": 78.35820895522389,
        "t1_number_of_solutions": 39,
        "t2_number_of_solutions": 35,
        "t3_number_of_solutions": 42,
        "number_of_final_solutions": 13,
        "results": [
            0.1,
            0.07692307692307693,
            0.08695652173913043,
            null
        ]
    },
    {
        "id": 48,
        "t1_average_reward": 14.925373134328359,
        "t2_average_reward": 89.55223880597015,
        "t3_average_reward": 88.80597014925372,
        "t1_number_of_solutions": 45,
        "t2_number_of_solutions": 44,
        "t3_number_of_solutions": 45,
        "number_of_final_solutions": 21,
        "results": [
            0.5,
            0.23809523809523808,
            0.3225806451612903,
            null
        ]
    }
]